{
  "seq": 19,
  "uid": "U-1030",
  "type": "definition",
  "claim_status": null,
  "label": "Function F_epsilon(x)",
  "path": "/home/wlloyd/Cella Framework/Papers_Library/02_theorems_and_lemmas/dbp_periods_landen_and_elliptic_structure/DBP_LANDEN_TRACE_THEOREM_COMPLETE_v1.1.md",
  "already_linked_objects": [
    {
      "id": "OBJ:bar-m-epsilon",
      "label": "bar m_epsilon"
    },
    {
      "id": "OBJ:f-epsilon",
      "label": "f_epsilon"
    },
    {
      "id": "OBJ:f-epsilon-x",
      "label": "F_epsilon(x)"
    },
    {
      "id": "OBJ:m-epsilon-n-epsilon-a-epsilon-b-epsilon",
      "label": "m_epsilon, n_epsilon, A_epsilon, B_epsilon"
    },
    {
      "id": "OBJ:u-a-epsilon-b-weierstrass-model-coordinates",
      "label": "u, a_epsilon, b (Weierstrass-model coordinates)"
    }
  ],
  "priority_candidate_pairs": [
    {
      "a": "OBJ:f-epsilon",
      "b": "OBJ:u-a-epsilon-b-weierstrass-model-coordinates",
      "la": "f_epsilon",
      "lb": "u, a_epsilon, b (Weierstrass-model coordinates)",
      "lift": 21.83
    },
    {
      "a": "OBJ:f-epsilon-x",
      "b": "OBJ:u-a-epsilon-b-weierstrass-model-coordinates",
      "la": "F_epsilon(x)",
      "lb": "u, a_epsilon, b (Weierstrass-model coordinates)",
      "lift": 21.83
    }
  ]
}