{"broad_entries": ["-1", "0", "1"], "byte_stable": true, "campaign": "campaign_g_rolechspec_gauge_obstruction_faithfulness", "campaign_f_retrodicted": true, "claims": {"CL-G1": {"statement": "ker(O_g)=Im(G_g) by exact construction; two computations agree", "verdict": "PASS"}, "CL-G2": {"retrodiction": {"0": [0, 1917], "1": [2549, 0], "2": [832, 0]}, "statement": "Campaign F obstruction split retrodicted", "verdict": "PASS"}, "CL-G3": {"gauge_invariance_counterexamples": 0, "statement": "O=0 implies RoleChSpec equal (gauge invariance)", "verdict": "PASS"}, "CL-G4": {"faithfulness_counterexamples": 0, "statement": "faithfulness: no O!=0 with RoleChSpec equal found", "verdict": "PASS"}, "CL-G5": {"statement": "all singularities typed (REGULAR/ROLE_CHART_UNAVAILABLE/SINGULAR_GRADIENT/OUT_OF_SCOPE); no raw exceptions", "verdict": "PASS"}, "CL-G6": {"self_glue_stage": "PASS", "statement": "self-glue structured families sampled and stressed", "verdict": "PASS"}, "CL-G7": {"evidence": "tests/test_campaign_g_non_tautology.py", "statement": "RoleChSpec recomputed (no cached labels); no float in equality path", "verdict": "PASS"}, "CL-G8": {"evidence": "tests/test_campaign_g_mutants.py", "statement": "10 mutation controls caught", "verdict": "PASS"}}, "deep_sweep": {"entries": ["-2", "-1", "0", "1", "2"], "g": ["1", "1", "1"]}, "discipline": {"eval_tier_only": true, "exact_Q": true, "no_float": true, "rolechspec_recomputed": true, "substrate_modified": false}, "faithfulness_counterexamples": 0, "float_free": true, "gauge_invariance_counterexamples": 0, "gradients_swept": [["1", "1", "1"], ["1", "2", "3"], ["2", "-1", "1"], ["1", "-2", "3"], ["2", "3", "5"], ["-1", "2", "1"]], "kill_conditions_fired": [], "mutations_caught": 10, "outcome": "A_theorem_survives", "pairs_tested": 751, "refusals_typed": true, "regular_pairs_tested": 19999, "retrodiction": {"0": [0, 1917], "1": [2549, 0], "2": [832, 0]}, "schema": "rolechspec_gauge_obstruction_faithfulness_summary_v1", "self_glue_structured_stage": "PASS", "status": "PASS"}
